pyhmmer/__init__.py
pyhmmer/easel.pxd
pyhmmer/easel.pyi
pyhmmer/easel.pypy37-pp73-darwin.so
pyhmmer/easel.pyx
pyhmmer/errors.pyi
pyhmmer/errors.pypy37-pp73-darwin.so
pyhmmer/errors.pyx
pyhmmer/exceptions.pxi
pyhmmer/hmmer.py
pyhmmer/plan7.pxd
pyhmmer/plan7.pyi
pyhmmer/plan7.pypy37-pp73-darwin.so
pyhmmer/plan7.pyx
pyhmmer/py.typed
pyhmmer/utils.py
pyhmmer/fileobj/bsd.pxi
pyhmmer/fileobj/linux.pxi
pyhmmer/reexports/__init__.pxd
pyhmmer/reexports/p7_hmmfile.h
pyhmmer/reexports/p7_hmmfile.pxd
pyhmmer/reexports/p7_tophits.h
pyhmmer/reexports/p7_tophits.pxd
pyhmmer_sepp-0.3.4.dist-info/COPYING
pyhmmer_sepp-0.3.4.dist-info/METADATA
pyhmmer_sepp-0.3.4.dist-info/WHEEL
pyhmmer_sepp-0.3.4.dist-info/top_level.txt
pyhmmer_sepp-0.3.4.dist-info/RECORD
