Metadata-Version: 2.1
Name: pyhmmer-sepp
Version: 0.3.4
Summary: Personal use fork of pyhmmer (Cython bindings and Python interface to HMMER3) for implementing SEPP
Home-page: https://github.com/RuneBlaze/pyhmmer
Author: Martin Larralde, RuneBlaze
License: MIT
Project-URL: Documentation, https://pyhmmer.readthedocs.io/en/stable/
Keywords: bioinformatics,profile,HMM,sequence,pfam
Platform: posix
Classifier: Development Status :: 4 - Beta
Classifier: Intended Audience :: Developers
Classifier: Intended Audience :: Science/Research
Classifier: License :: OSI Approved :: MIT License
Classifier: Operating System :: POSIX
Classifier: Programming Language :: C
Classifier: Programming Language :: Cython
Classifier: Programming Language :: Python :: 3.6
Classifier: Programming Language :: Python :: 3.7
Classifier: Programming Language :: Python :: 3.8
Classifier: Programming Language :: Python :: 3.9
Classifier: Programming Language :: Python :: Implementation :: CPython
Classifier: Programming Language :: Python :: Implementation :: PyPy
Classifier: Topic :: Scientific/Engineering :: Bio-Informatics
Classifier: Topic :: Scientific/Engineering :: Medical Science Apps.
Classifier: Typing :: Typed
Requires-Python: >=3.6
